spcoral/__init__.py
spcoral/utils.py
spcoral/analysis/__init__.py
spcoral/analysis/correlation.py
spcoral/analysis/mapping.py
spcoral/analysis/spatial_domain.py
spcoral/model/HANConv.py
spcoral/model/__init__.py
spcoral/model/gat_code.py
spcoral/model/model.py
spcoral/model/network.py
spcoral/model/regist.py
spcoral/model/utils.py
spcoral/plot/_3d.py
spcoral/plot/__init__.py
spcoral/plot/_heatmap.py
spcoral/plot/_sankey.py
spcoral/plot/color.py
spcoral/plot/integrate_map.py
spcoral/plot/situ_map.py
spcoral/pp/__init__.py
spcoral/pp/clipping.py
spcoral/pp/down_sample.py
spcoral/pp/int_preprocess.py
spcoral/pp/spatial_variable.py
spcoral-0.0.1.dist-info/METADATA
spcoral-0.0.1.dist-info/WHEEL
spcoral-0.0.1.dist-info/top_level.txt
spcoral-0.0.1.dist-info/RECORD
