Metadata-Version: 2.4
Name: spcoral
Version: 0.0.1
Summary: A python package for registering and integrating cross-model spatial omics
Author-email: Heqi Wang <wangheqi2021@sinh.ac.cn>
License: AGPL-3.0
Project-URL: Homepage, https://github.com/LiHongCSBLab/SPCoral
Project-URL: Repository, https://github.com/LiHongCSBLab/SPCoral
Keywords: bio-informatics,spatial multi-omics,spatial transcriptomics,spatial data analysis,Alignment,Integration
Classifier: Development Status :: 3 - Alpha
Classifier: Intended Audience :: Developers
Classifier: Natural Language :: English
Classifier: Programming Language :: Python :: 3
Classifier: Programming Language :: Python :: 3.9
Classifier: Programming Language :: Python :: 3.10
Classifier: Programming Language :: Python :: 3.11
Classifier: Programming Language :: Python :: 3.12
Classifier: License :: OSI Approved :: GNU Affero General Public License v3
Classifier: Topic :: Scientific/Engineering :: Bio-Informatics
Requires-Python: >=3.9
Requires-Dist: anndata==0.10.9
Requires-Dist: numpy==1.26.4
Requires-Dist: networkx==3.2.1
Requires-Dist: scikit-learn==1.5.1
Requires-Dist: scikit-misc==0.3.1
Requires-Dist: scipy==1.12.0
Requires-Dist: seaborn==0.13.2
Requires-Dist: tqdm==4.66.4
Requires-Dist: pandas==2.0
Requires-Dist: scanpy==1.10.3
Requires-Dist: decorator
